tap_twilio/__init__.py
tap_twilio/client.py
tap_twilio/discover.py
tap_twilio/schema.py
tap_twilio/streams.py
tap_twilio/sync.py
tap_twilio/transform.py
tap_twilio/schemas/account_balance.json
tap_twilio/schemas/accounts.json
tap_twilio/schemas/activities.json
tap_twilio/schemas/addresses.json
tap_twilio/schemas/alerts.json
tap_twilio/schemas/applications.json
tap_twilio/schemas/available_phone_number_countries.json
tap_twilio/schemas/available_phone_numbers_local.json
tap_twilio/schemas/available_phone_numbers_mobile.json
tap_twilio/schemas/available_phone_numbers_toll_free.json
tap_twilio/schemas/calls.json
tap_twilio/schemas/channels.json
tap_twilio/schemas/chat_channels.json
tap_twilio/schemas/chat_messages.json
tap_twilio/schemas/conference_participants.json
tap_twilio/schemas/conferences.json
tap_twilio/schemas/cumulative_statistics.json
tap_twilio/schemas/dependent_phone_numbers.json
tap_twilio/schemas/events.json
tap_twilio/schemas/incoming_phone_numbers.json
tap_twilio/schemas/keys.json
tap_twilio/schemas/members.json
tap_twilio/schemas/message_media.json
tap_twilio/schemas/messages.json
tap_twilio/schemas/outgoing_caller_ids.json
tap_twilio/schemas/queues.json
tap_twilio/schemas/recordings.json
tap_twilio/schemas/roles.json
tap_twilio/schemas/services.json
tap_twilio/schemas/task_channels.json
tap_twilio/schemas/task_queues.json
tap_twilio/schemas/tasks.json
tap_twilio/schemas/transcriptions.json
tap_twilio/schemas/usage.json
tap_twilio/schemas/usage_records.json
tap_twilio/schemas/usage_triggers.json
tap_twilio/schemas/users.json
tap_twilio/schemas/workers.json
tap_twilio/schemas/workflows.json
tap_twilio/schemas/workspaces.json
tests/__init__.py
tests/test_configuration.py
tests/test_sync.py
pipelinewise_tap_twilio-1.1.2.dist-info/LICENSE
pipelinewise_tap_twilio-1.1.2.dist-info/METADATA
pipelinewise_tap_twilio-1.1.2.dist-info/WHEEL
pipelinewise_tap_twilio-1.1.2.dist-info/entry_points.txt
pipelinewise_tap_twilio-1.1.2.dist-info/top_level.txt
pipelinewise_tap_twilio-1.1.2.dist-info/RECORD
