Metadata-Version: 2.1
Name: pipelinewise-tap-twilio
Version: 1.1.2
Summary: Singer.io tap for extracting data from the Twilio API - PipelineWise compatible
Home-page: https://github.com/transferwise/pipelinewise-tap-twilio
Author: Wise
License: UNKNOWN
Platform: UNKNOWN
Classifier: License :: OSI Approved :: GNU Affero General Public License v3
Classifier: Programming Language :: Python :: 3 :: Only
Requires-Dist: requests (==2.25.1)
Requires-Dist: pipelinewise-singer-python (==1.*)
Provides-Extra: test
Requires-Dist: pylint ; extra == 'test'
Requires-Dist: pytest ; extra == 'test'
